__init__.py
mond/__init__.py
mond/box.py
mond/utils.py
mond/docking/__init__.py
mond/docking/dissolve.py
mond/docking/dock.py
mond/docking/xtb.py
mond/molecule/__init__.py
mond/molecule/molecule.py
mond/openmm/__init__.py
mond/openmm/simulation.py
mond/packing/__init__.py
mond/packing/pack.py
mond/simulation/aimd.py
mond-0.2.5.dist-info/licenses/LICENSE
mond-0.2.5.dist-info/METADATA
mond-0.2.5.dist-info/WHEEL
mond-0.2.5.dist-info/top_level.txt
mond-0.2.5.dist-info/RECORD
