Metadata-Version: 2.4
Name: mond
Version: 0.2.5
Summary: Monte Carlo Simulation to dissolve a molecule in a mixture of other molecules
Author-email: "Julian M. Kleber" <julian.m.kleber@gmail.com>
Project-URL: Homepage, https://www.codeberg.org/cap_jmk/mond.git
Project-URL: Bug Tracker, https://www.codeberg.org/cap_jmk/mond.git/issues
Classifier: Programming Language :: Python :: 3
Classifier: License :: OSI Approved :: GNU General Public License v3 (GPLv3)
Classifier: Operating System :: OS Independent
Requires-Python: >=3.8
License-File: LICENSE
Requires-Dist: numpy
Requires-Dist: cryptography
Requires-Dist: applique
Requires-Dist: amarium
Requires-Dist: tqdm
Requires-Dist: scipy
Dynamic: license-file
